pygazpar/__init__.py
pygazpar/__main__.py
pygazpar/auth.py
pygazpar/client.py
pygazpar/consommation.py
pygazpar/datasource.py
pygazpar/enum.py
pygazpar/excelparser.py
pygazpar/exceptions.py
pygazpar/frequency.py
pygazpar/helpers.py
pygazpar/jsonparser.py
pygazpar/pce.py
pygazpar/version.py
pygazpar/resources/daily_data_sample.json
pygazpar/resources/hourly_data_sample.json
pygazpar/resources/monthly_data_sample.json
pygazpar/resources/weekly_data_sample.json
pygazpar/resources/yearly_data_sample.json
pygazpar/types/ConsommationReference.py
pygazpar/types/ConsommationType.py
pygazpar/types/ContratType.py
pygazpar/types/DetailsPceType.py
pygazpar/types/PceType.py
pygazpar/types/RelevesResultType.py
pygazpar/types/__init__.py
samples/__init__.py
samples/excelSample.py
samples/jsonSample.py
samples/testSample.py
tests/__init__.py
tests/test_client.py
tests/test_datafileparser.py
tests/test_datasource.py
apiGazpar-2.0.12.dist-info/LICENSE.md
apiGazpar-2.0.12.dist-info/METADATA
apiGazpar-2.0.12.dist-info/WHEEL
apiGazpar-2.0.12.dist-info/entry_points.txt
apiGazpar-2.0.12.dist-info/top_level.txt
apiGazpar-2.0.12.dist-info/RECORD
