Metadata-Version: 2.1
Name: apiGazpar
Version: 2.0.12
Summary: Retrieve gas consumption from GrDF web site (French Gas Company)
Home-page: https://github.com/flocmoi09/apiGazpar
Download-URL: https://github.com/flocmoi09/apiGazpar/releases
Author: Florent Courtois
Author-email: flocmoi09@gmail.com
License: MIT
Project-URL: Home, https://github.com/flocmoi09/apiGazpar
Project-URL: Source, https://github.com/flocmoi09/apiGazpar
Project-URL: Issues, https://github.com/flocmoi09/apiGazpar/issues
Project-URL: Changelog, https://github.com/flocmoi09/apiGazpar/blob/master/CHANGELOG.md
Project-URL: Download, https://pypi.org/project/pygazpar
Keywords: Energy,Natural Gas,Meter,GrDF,Gazpar
Platform: any
Classifier: Development Status :: 5 - Production/Stable
Classifier: Topic :: Software Development :: Libraries
Classifier: Operating System :: OS Independent
Classifier: Programming Language :: Python :: 3.7
Classifier: Programming Language :: Python :: 3.8
Classifier: Programming Language :: Python :: 3.9
Classifier: Programming Language :: Python :: 3.10
Classifier: Programming Language :: Python :: 3.11
Classifier: Programming Language :: Python :: 3.12
Requires-Python: >=3.7
License-File: LICENSE.md
Requires-Dist: openpyxl>=2.6.3
Requires-Dist: requests>=2.26.0
Requires-Dist: pandas
